net_tracer/__init__.py
net_tracer/scan.py
net_tracer-1.0.5.dist-info/LICENSE
net_tracer-1.0.5.dist-info/METADATA
net_tracer-1.0.5.dist-info/WHEEL
net_tracer-1.0.5.dist-info/top_level.txt
net_tracer-1.0.5.dist-info/RECORD
