Metadata-Version: 2.1
Name: net-tracer
Version: 1.0.5
Summary: A Python tool for Network Security
Home-page: https://github.com/Morbid1134/Net-Tracer
Author: Morbid
Author-email: ethan.smith31415@gmail.com
Classifier: Programming Language :: Python :: 3
Classifier: License :: OSI Approved :: MIT License
Classifier: Operating System :: OS Independent
Requires-Python: >=3.6
License-File: LICENSE
Requires-Dist: python-nmap
Requires-Dist: pyfiglet
